verilog/design_narma.sv
// LFSR Module for Generating Pseudo-Random Input
module lfsr_random_input (
  input wire clk,
  input wire rst,
  output reg [15:0] lfsr_out
);
  reg [15:0] lfsr = 16'hACE1; // Initial seed for LFSR
  
  always @(posedge clk or posedge rst) begin
    if (rst) begin
      lfsr <= 16'hACE1; // Reset LFSR to initial seed
    end else begin
      // Feedback calculation for 16-bit LFSR (x^16 + x^14 + x^13 + x^11 + 1)
      lfsr <= {lfsr[14:0], lfsr[15] ^ lfsr[13] ^ lfsr[12] ^ lfsr[10]};
    end
    lfsr_out <= lfsr >> 1; // Scale to range [0, 0.5] by dividing by 2
  end
endmodule


// NARMA-10 Generator Module
module narma10_generator (
  input wire clk,
  input wire rst,
  input wire [15:0] u_t, // Input from LFSR
  output reg [15:0] y_t // 16-bit output representing the NARMA output
);
  parameter N = 10; // Order of the NARMA series
  reg [15:0] y_history [0:N-1]; // Buffer to hold past outputs
  reg [15:0] u_history [0:N-1]; // Buffer to hold past inputs
  
  integer i;
  
  always @(posedge clk or posedge rst) begin
    if (rst) begin
      // Initialize histories
      for (i = 0; i < N; i = i + 1) begin
        y_history[i] <= 16'd0;
        u_history[i] <= 16'd0;
      end
      y_t <= 16'd0;
    end else begin
      // Shift history buffers
      for (i = N-1; i > 0; i = i - 1) begin
        y_history[i] <= y_history[i-1];
        u_history[i] <= u_history[i-1];
      end
      u_history[0] <= u_t;
      
      // NARMA-10 computation: y(t+1) = 0.5*y(t) + 0.3*y(t) * sum(y(t-1) to y(t-9)) + 0.8*u(t-9)*u(t) + 0.1
      y_t <= (5 * y_history[0] / 10) +
      ((3 * y_history[0] * (y_history[1] + y_history[2] + y_history[3] +
                            y_history[4] + y_history[5] + y_history[6] +
                            y_history[7] + y_history[8] + y_history[9])) / 10) +
      (8 * u_history[9] * u_history[0] / 10) +
      (1 << 10); // Adding 0.1 as fixed-point representation
      y_history[0] <= y_t; 
    end
  end
endmodule


// Top-level Module to Integrate LFSR with NARMA
module top_level_narma_system (
  input wire clk,
  input wire rst,
  output wire [15:0] narma_output
);
  wire [15:0] lfsr_output;
  
  // Instantiate LFSR module
  lfsr_random_input lfsr_inst (
    .clk(clk),
    .rst(rst),
    .lfsr_out(lfsr_output)
  );
  
  // Instantiate NARMA-10 generator module
  narma10_generator narma_gen (
    .clk(clk),
    .rst(rst),
    .u_t(lfsr_output),
    .y_t(narma_output)
  );
endmodule



module bitstream_converter (
  input wire [15:0] y_t,
  output reg [31:0] bitstream_out
);
  integer num_on_bits;
  integer i;
  
  always @(*) begin
    // Scale y_t to determine the number of "on" bits in the 32-bit output.
    // The scaling factor should map y_t's maximum value to 32 bits fully "on".
    num_on_bits = (y_t * 32) >> 16; // Ensure y_t is scaled proportionally to 32-bit range

    // Initialize bitstream_out with all bits off
    bitstream_out = 32'b0;

    // Turn on the calculated number of bits from the most significant bit down
    for (i = 0; i < num_on_bits; i = i + 1) begin
      bitstream_out[i] = 1'b1;
    end
  end
endmodule


module lif_neuron(i_in, ext_input, clk, rst, VOUT, i_out);
  input [7:0] i_in; // Allow 8 input signals, represented as on/off
  input [31:0] ext_input;      // 32-bit bitstream input from ARMA function
  input clk, rst;
  output reg signed [31:0] VOUT; // The voltage across this neuron
  output reg i_out; // Output signal

  // initial condition
  reg signed [31:0] v = 	32'h00000000; // v=0;

  // LIF parameters
  reg signed [31:0] Vth = 	32'h0000fc93; // Threshold voltage = 0.98
  reg signed [31:0] leaky = 32'h00002000; // Leakage = 0.125
  reg signed [31:0] w = 	32'h00002000; // Input weight = 0.125
  reg signed [31:0] ext_w = 32'h00001000; // Weight for ext_input = 0.0625 (lower than 0.125)

  integer n;
  reg signed [31:0] a; // Adder output
  reg signed [31:0] ext_a; // Adder output for ext_input

  // clock
  parameter s0 = 8'h00;
  parameter s1 = 8'h01;
  parameter s2 = 8'h02;

  wire [7:0] p_s;
  reg [7:0] n_s;

  assign p_s = n_s;
  always @(posedge clk or negedge rst)
  begin
      if (!rst)
          n_s <= s0;
      else if (clk)
      begin
          case (p_s)
              s0: begin
                  // Idle / refractory period
                  i_out <= 1'b0;
                  n_s <= s1;
              end
              s1: begin
                // Accumulate weighted inputs
                a = 32'h00000000;
                for (n = 0; n < 8; n++)
                  begin
                      a = a + (i_in[n] * w);
                  end
                // Accumulate weighted inputs from ext_input
                ext_a = 32'h00000000;
                for (n = 0; n < 32; n = n + 1) begin
                  ext_a = ext_a + (ext_input[n] * ext_w);
                end
                // Integrate
                if (a + ext_a > 0)
                  begin
                      v <= v + a + ext_a;
                  end
                  // Leaky
                  else if (v > 0)
                  begin
                      v <= v - leaky;
                      // Ensure that v >= 0
                      if (v < 0)
                      begin
                          v <= 32'h00000000;
                      end
                  end

                  VOUT <= v;

                  if (v >= Vth)
                  begin
                      n_s <= s2;
                  end
              end
              s2: begin
                  // Fire
                  v <= 32'h00000000;
                  VOUT <= 32'h00000000;
                  i_out <= 1'b1;
                  n_s <= s0;
              end
          endcase
      end
  end
endmodule

verilog/testbench_narma.sv
`timescale 1ns/1ps

module tb_top_level_narma_system;
  // Testbench signals
  reg clk = 1'b0;
  reg rst;
  wire [15:0] narma_output;
  wire [31:0] narma_bitstream;
  reg [31:0] ext_input = 32'h00000000;
  wire [9:0] i_outs;    // Outputs from each neuron, connected cyclically. Size = N neurons
  
  // Output wires from each neuron
  wire signed [31:0] VOUT1, VOUT2, VOUT3, VOUT4, VOUT5;
  wire signed [31:0] VOUT6, VOUT7, VOUT8, VOUT9, VOUT10;
  reg [7:0] sp_in_1, sp_in_2, sp_in_3, sp_in_4, sp_in_5;
  reg [7:0] sp_in_6, sp_in_7, sp_in_8, sp_in_9, sp_in_10;
  
  // File handle for CSV output
  integer csv_file;
  
  // Instantiate the top-level NARMA system
  top_level_narma_system uut (
    .clk(clk),
    .rst(rst),
    .narma_output(narma_output)
  );
  
  // Instantiate bitstream converter
  bitstream_converter converter (
    .y_t(narma_output),
    .bitstream_out(narma_bitstream)
  );
  
  // Instantiate 10 LIF neurons and connect them cyclically
  lif_neuron neuron1(
    .i_in(sp_in_1), // Input connected to output of neuron10
    .ext_input(ext_input),
    .clk(clk),
    .rst(rst),
    .VOUT(VOUT1),
    .i_out(i_outs[0])
  );

  lif_neuron neuron2(
    .i_in(sp_in_2),
    .ext_input(ext_input),
    .clk(clk),
    .rst(rst),
    .VOUT(VOUT2),
    .i_out(i_outs[1])
  );

  lif_neuron neuron3(
    .i_in(sp_in_3),
    .ext_input(ext_input),
    .clk(clk),
    .rst(rst),
    .VOUT(VOUT3),
    .i_out(i_outs[2])
  );
  
  lif_neuron neuron4(
    .i_in(sp_in_4),
    .ext_input(ext_input),
    .clk(clk),
    .rst(rst),
    .VOUT(VOUT4),
    .i_out(i_outs[3])
  );

  lif_neuron neuron5(
    .i_in(sp_in_5),
    .ext_input(ext_input),
    .clk(clk),
    .rst(rst),
    .VOUT(VOUT5),
    .i_out(i_outs[4])
  );

  lif_neuron neuron6(
    .i_in(sp_in_6),
    .ext_input(ext_input),
    .clk(clk),
    .rst(rst),
    .VOUT(VOUT6),
    .i_out(i_outs[5])
  );
  
  lif_neuron neuron7(
    .i_in(sp_in_7),
    .ext_input(ext_input),
    .clk(clk),
    .rst(rst),
    .VOUT(VOUT7),
    .i_out(i_outs[6])
  );

  lif_neuron neuron8(
    .i_in(sp_in_8),
    .ext_input(ext_input),
    .clk(clk),
    .rst(rst),
    .VOUT(VOUT8),
    .i_out(i_outs[7])
  );

  lif_neuron neuron9(
    .i_in(sp_in_9),
    .ext_input(ext_input),
    .clk(clk),
    .rst(rst),
    .VOUT(VOUT9),
    .i_out(i_outs[8])
  );

  lif_neuron neuron10(
    .i_in(sp_in_10),
    .ext_input(ext_input),
    .clk(clk),
    .rst(rst),
    .VOUT(VOUT10),
    .i_out(i_outs[9])
  );
  
  // Test procedure
  initial begin
    
    // Open CSV file for writing
    csv_file = $fopen("output_waveforms_narma.csv", "w");
    if (!csv_file) begin
      $display("Error: Could not open CSV file for writing.");
      $finish;
    end
    
    // Write CSV header
    $fwrite(csv_file, "Time (ns), NARMA Output (Float), Bits\n");
    
    // Initialize waveform dumping for simulation
    $dumpfile("tb_top_level_narma_system.vcd");
    $dumpvars(0, tb_top_level_narma_system);
    
    // Reset sequence
    rst = 1;

    #5; // Hold reset for 20ns
    rst = 0;
    
    // Run simulation for a certain duration
    #20000; // Run for 2000ns
    
    // Close the CSV file
    $fclose(csv_file);
    
    // End simulation
    $finish;
  end
  
  always
    begin
      #50 clk = ~clk; // Generate clock signal with 90 time unit period
      
      ext_input = narma_bitstream;
      
      sp_in_1 = {7'b0, i_outs[9]};
      sp_in_2 = {7'b0, i_outs[0]};
      sp_in_3 = {7'b0, i_outs[1]};
      sp_in_4 = {7'b0, i_outs[2]};
      sp_in_5 = {7'b0, i_outs[3]};
      sp_in_6 = {7'b0, i_outs[4]};
      sp_in_7 = {7'b0, i_outs[5]};
      sp_in_8 = {7'b0, i_outs[6]};
      sp_in_9 = {7'b0, i_outs[7]};
      sp_in_10 = {7'b0, i_outs[8]};
  end

  integer i;

  // Monitor outputs in floats and write to CSV
  always @(posedge clk) begin
    if (!rst) begin
      $fwrite(csv_file, "%0t, %0f", $time, convert_to_real(narma_output));
      for (i = 0; i < 10; i = i + 1) begin
        $fwrite(csv_file, ", %0b", i_outs[i]);
      end
      $fwrite(csv_file, "\n");
    end
  end
    
    
  // Optional: Conversion to float representation if needed
  function real convert_to_real(input [15:0] fixed_point_value);
    begin
      // Assumes the fixed-point value is scaled (divide by 2^10 to convert)
      convert_to_real = fixed_point_value / 1024.0;
    end
  endfunction
endmodule

tb_top_level_narma_system.vcd
$date
	Wed Nov 27 16:33:20 2024
$end
$version
	Icarus Verilog
$end
$timescale
	1ps
$end
$scope module tb_top_level_narma_system $end
$var wire 16 ! narma_output [15:0] $end
$var wire 32 " narma_bitstream [31:0] $end
$var wire 10 # i_outs [9:0] $end
$var wire 32 $ VOUT9 [31:0] $end
$var wire 32 % VOUT8 [31:0] $end
$var wire 32 & VOUT7 [31:0] $end
$var wire 32 ' VOUT6 [31:0] $end
$var wire 32 ( VOUT5 [31:0] $end
$var wire 32 ) VOUT4 [31:0] $end
$var wire 32 * VOUT3 [31:0] $end
$var wire 32 + VOUT2 [31:0] $end
$var wire 32 , VOUT10 [31:0] $end
$var wire 32 - VOUT1 [31:0] $end
$var reg 1 . clk $end
$var reg 32 / ext_input [31:0] $end
$var reg 1 0 rst $end
$var reg 8 1 sp_in_1 [7:0] $end
$var reg 8 2 sp_in_10 [7:0] $end
$var reg 8 3 sp_in_2 [7:0] $end
$var reg 8 4 sp_in_3 [7:0] $end
$var reg 8 5 sp_in_4 [7:0] $end
$var reg 8 6 sp_in_5 [7:0] $end
$var reg 8 7 sp_in_6 [7:0] $end
$var reg 8 8 sp_in_7 [7:0] $end
$var reg 8 9 sp_in_8 [7:0] $end
$var reg 8 : sp_in_9 [7:0] $end
$var integer 32 ; csv_file [31:0] $end
$var integer 32 < i [31:0] $end
$scope function convert_to_real $end
$var reg 16 = fixed_point_value [15:0] $end
$upscope $end
$scope module converter $end
$var wire 16 > y_t [15:0] $end
$var reg 32 ? bitstream_out [31:0] $end
$var integer 32 @ i [31:0] $end
$var integer 32 A num_on_bits [31:0] $end
$upscope $end
$scope module neuron1 $end
$var wire 1 . clk $end
$var wire 32 B ext_input [31:0] $end
$var wire 8 C i_in [7:0] $end
$var wire 8 D p_s [7:0] $end
$var wire 1 0 rst $end
$var parameter 8 E s0 $end
$var parameter 8 F s1 $end
$var parameter 8 G s2 $end
$var reg 32 H VOUT [31:0] $end
$var reg 32 I Vth [31:0] $end
$var reg 32 J a [31:0] $end
$var reg 32 K ext_a [31:0] $end
$var reg 32 L ext_w [31:0] $end
$var reg 1 M i_out $end
$var reg 32 N leaky [31:0] $end
$var reg 8 O n_s [7:0] $end
$var reg 32 P v [31:0] $end
$var reg 32 Q w [31:0] $end
$var integer 32 R n [31:0] $end
$upscope $end
$scope module neuron10 $end
$var wire 1 . clk $end
$var wire 32 S ext_input [31:0] $end
$var wire 8 T i_in [7:0] $end
$var wire 8 U p_s [7:0] $end
$var wire 1 0 rst $end
$var parameter 8 V s0 $end
$var parameter 8 W s1 $end
$var parameter 8 X s2 $end
$var reg 32 Y VOUT [31:0] $end
$var reg 32 Z Vth [31:0] $end
$var reg 32 [ a [31:0] $end
$var reg 32 \ ext_a [31:0] $end
$var reg 32 ] ext_w [31:0] $end
$var reg 1 ^ i_out $end
$var reg 32 _ leaky [31:0] $end
$var reg 8 ` n_s [7:0] $end
$var reg 32 a v [31:0] $end
$var reg 32 b w [31:0] $end
$var integer 32 c n [31:0] $end
$upscope $end
$scope module neuron2 $end
$var wire 1 . clk $end
$var wire 32 d ext_input [31:0] $end
$var wire 8 e i_in [7:0] $end
$var wire 8 f p_s [7:0] $end
$var wire 1 0 rst $end
$var parameter 8 g s0 $end
$var parameter 8 h s1 $end
$var parameter 8 i s2 $end
$var reg 32 j VOUT [31:0] $end
$var reg 32 k Vth [31:0] $end
$var reg 32 l a [31:0] $end
$var reg 32 m ext_a [31:0] $end
$var reg 32 n ext_w [31:0] $end
$var reg 1 o i_out $end
$var reg 32 p leaky [31:0] $end
$var reg 8 q n_s [7:0] $end
$var reg 32 r v [31:0] $end
$var reg 32 s w [31:0] $end
$var integer 32 t n [31:0] $end
$upscope $end
$scope module neuron3 $end
$var wire 1 . clk $end
$var wire 32 u ext_input [31:0] $end
$var wire 8 v i_in [7:0] $end
$var wire 8 w p_s [7:0] $end
$var wire 1 0 rst $end
$var parameter 8 x s0 $end
$var parameter 8 y s1 $end
$var parameter 8 z s2 $end
$var reg 32 { VOUT [31:0] $end
$var reg 32 | Vth [31:0] $end
$var reg 32 } a [31:0] $end
$var reg 32 ~ ext_a [31:0] $end
$var reg 32 !" ext_w [31:0] $end
$var reg 1 "" i_out $end
$var reg 32 #" leaky [31:0] $end
$var reg 8 $" n_s [7:0] $end
$var reg 32 %" v [31:0] $end
$var reg 32 &" w [31:0] $end
$var integer 32 '" n [31:0] $end
$upscope $end
$scope module neuron4 $end
$var wire 1 . clk $end
$var wire 32 (" ext_input [31:0] $end
$var wire 8 )" i_in [7:0] $end
$var wire 8 *" p_s [7:0] $end
$var wire 1 0 rst $end
$var parameter 8 +" s0 $end
$var parameter 8 ," s1 $end
$var parameter 8 -" s2 $end
$var reg 32 ." VOUT [31:0] $end
$var reg 32 /" Vth [31:0] $end
$var reg 32 0" a [31:0] $end
$var reg 32 1" ext_a [31:0] $end
$var reg 32 2" ext_w [31:0] $end
$var reg 1 3" i_out $end
$var reg 32 4" leaky [31:0] $end
$var reg 8 5" n_s [7:0] $end
$var reg 32 6" v [31:0] $end
$var reg 32 7" w [31:0] $end
$var integer 32 8" n [31:0] $end
$upscope $end
$scope module neuron5 $end
$var wire 1 . clk $end
$var wire 32 9" ext_input [31:0] $end
$var wire 8 :" i_in [7:0] $end
$var wire 8 ;" p_s [7:0] $end
$var wire 1 0 rst $end
$var parameter 8 <" s0 $end
$var parameter 8 =" s1 $end
$var parameter 8 >" s2 $end
$var reg 32 ?" VOUT [31:0] $end
$var reg 32 @" Vth [31:0] $end
$var reg 32 A" a [31:0] $end
$var reg 32 B" ext_a [31:0] $end
$var reg 32 C" ext_w [31:0] $end
$var reg 1 D" i_out $end
$var reg 32 E" leaky [31:0] $end
$var reg 8 F" n_s [7:0] $end
$var reg 32 G" v [31:0] $end
$var reg 32 H" w [31:0] $end
$var integer 32 I" n [31:0] $end
$upscope $end
$scope module neuron6 $end
$var wire 1 . clk $end
$var wire 32 J" ext_input [31:0] $end
$var wire 8 K" i_in [7:0] $end
$var wire 8 L" p_s [7:0] $end
$var wire 1 0 rst $end
$var parameter 8 M" s0 $end
$var parameter 8 N" s1 $end
$var parameter 8 O" s2 $end
$var reg 32 P" VOUT [31:0] $end
$var reg 32 Q" Vth [31:0] $end
$var reg 32 R" a [31:0] $end
$var reg 32 S" ext_a [31:0] $end
$var reg 32 T" ext_w [31:0] $end
$var reg 1 U" i_out $end
$var reg 32 V" leaky [31:0] $end
$var reg 8 W" n_s [7:0] $end
$var reg 32 X" v [31:0] $end
$var reg 32 Y" w [31:0] $end
$var integer 32 Z" n [31:0] $end
$upscope $end
$scope module neuron7 $end
$var wire 1 . clk $end
$var wire 32 [" ext_input [31:0] $end
$var wire 8 \" i_in [7:0] $end
$var wire 8 ]" p_s [7:0] $end
$var wire 1 0 rst $end
$var parameter 8 ^" s0 $end
$var parameter 8 _" s1 $end
$var parameter 8 `" s2 $end
$var reg 32 a" VOUT [31:0] $end
$var reg 32 b" Vth [31:0] $end
$var reg 32 c" a [31:0] $end
$var reg 32 d" ext_a [31:0] $end
$var reg 32 e" ext_w [31:0] $end
$var reg 1 f" i_out $end
$var reg 32 g" leaky [31:0] $end
$var reg 8 h" n_s [7:0] $end
$var reg 32 i" v [31:0] $end
$var reg 32 j" w [31:0] $end
$var integer 32 k" n [31:0] $end
$upscope $end
$scope module neuron8 $end
$var wire 1 . clk $end
$var wire 32 l" ext_input [31:0] $end
$var wire 8 m" i_in [7:0] $end
$var wire 8 n" p_s [7:0] $end
$var wire 1 0 rst $end
$var parameter 8 o" s0 $end
$var parameter 8 p" s1 $end
$var parameter 8 q" s2 $end
$var reg 32 r" VOUT [31:0] $end
$var reg 32 s" Vth [31:0] $end
$var reg 32 t" a [31:0] $end
$var reg 32 u" ext_a [31:0] $end
$var reg 32 v" ext_w [31:0] $end
$var reg 1 w" i_out $end
$var reg 32 x" leaky [31:0] $end
$var reg 8 y" n_s [7:0] $end
$var reg 32 z" v [31:0] $end
$var reg 32 {" w [31:0] $end
$var integer 32 |" n [31:0] $end
$upscope $end
$scope module neuron9 $end
$var wire 1 . clk $end
$var wire 32 }" ext_input [31:0] $end
$var wire 8 ~" i_in [7:0] $end
$var wire 8 !# p_s [7:0] $end
$var wire 1 0 rst $end
$var parameter 8 "# s0 $end
$var parameter 8 ## s1 $end
$var parameter 8 $# s2 $end
$var reg 32 %# VOUT [31:0] $end
$var reg 32 &# Vth [31:0] $end
$var reg 32 '# a [31:0] $end
$var reg 32 (# ext_a [31:0] $end
$var reg 32 )# ext_w [31:0] $end
$var reg 1 *# i_out $end
$var reg 32 +# leaky [31:0] $end
$var reg 8 ,# n_s [7:0] $end
$var reg 32 -# v [31:0] $end
$var reg 32 .# w [31:0] $end
$var integer 32 /# n [31:0] $end
$upscope $end
$scope module uut $end
$var wire 1 . clk $end
$var wire 1 0 rst $end
$var wire 16 0# narma_output [15:0] $end
$var wire 16 1# lfsr_output [15:0] $end
$scope module lfsr_inst $end
$var wire 1 . clk $end
$var wire 1 0 rst $end
$var reg 16 2# lfsr [15:0] $end
$var reg 16 3# lfsr_out [15:0] $end
$upscope $end
$scope module narma_gen $end
$var wire 1 . clk $end
$var wire 1 0 rst $end
$var wire 16 4# u_t [15:0] $end
$var parameter 32 5# N $end
$var reg 16 6# y_t [15:0] $end
$var integer 32 7# i [31:0] $end
$upscope $end
$upscope $end
$upscope $end
$enddefinitions $end
$comment Show the parameter values. $end
$dumpall
b1010 5#
b10 $#
b1 ##
b0 "#
b10 q"
b1 p"
b0 o"
b10 `"
b1 _"
b0 ^"
b10 O"
b1 N"
b0 M"
b10 >"
b1 ="
b0 <"
b10 -"
b1 ,"
b0 +"
b10 z
b1 y
b0 x
b10 i
b1 h
b0 g
b10 X
b1 W
b0 V
b10 G
b1 F
b0 E
$end
#0
$dumpvars
b1010 7#
b0 6#
b101011001110000 4#
b101011001110000 3#
b1010110011100001 2#
b101011001110000 1#
b0 0#
bx /#
b10000000000000 .#
b0 -#
bx ,#
b10000000000000 +#
x*#
b1000000000000 )#
bx (#
bx '#
b1111110010010011 &#
bx %#
bx !#
bx ~"
b0 }"
bx |"
b10000000000000 {"
b0 z"
bx y"
b10000000000000 x"
xw"
b1000000000000 v"
bx u"
bx t"
b1111110010010011 s"
bx r"
bx n"
bx m"
b0 l"
bx k"
b10000000000000 j"
b0 i"
bx h"
b10000000000000 g"
xf"
b1000000000000 e"
bx d"
bx c"
b1111110010010011 b"
bx a"
bx ]"
bx \"
b0 ["
bx Z"
b10000000000000 Y"
b0 X"
bx W"
b10000000000000 V"
xU"
b1000000000000 T"
bx S"
bx R"
b1111110010010011 Q"
bx P"
bx L"
bx K"
b0 J"
bx I"
b10000000000000 H"
b0 G"
bx F"
b10000000000000 E"
xD"
b1000000000000 C"
bx B"
bx A"
b1111110010010011 @"
bx ?"
bx ;"
bx :"
b0 9"
bx 8"
b10000000000000 7"
b0 6"
bx 5"
b10000000000000 4"
x3"
b1000000000000 2"
bx 1"
bx 0"
b1111110010010011 /"
bx ."
bx *"
bx )"
b0 ("
bx '"
b10000000000000 &"
b0 %"
bx $"
b10000000000000 #"
x""
b1000000000000 !"
bx ~
bx }
b1111110010010011 |
bx {
bx w
bx v
b0 u
bx t
b10000000000000 s
b0 r
bx q
b10000000000000 p
xo
b1000000000000 n
bx m
bx l
b1111110010010011 k
bx j
bx f
bx e
b0 d
bx c
b10000000000000 b
b0 a
bx `
b10000000000000 _
x^
b1000000000000 ]
bx \
bx [
b1111110010010011 Z
bx Y
bx U
bx T
b0 S
bx R
b10000000000000 Q
b0 P
bx O
b10000000000000 N
xM
b1000000000000 L
bx K
bx J
b1111110010010011 I
bx H
bx D
bx C
b0 B
b0 A
b0 @
b0 ?
b0 >
bx =
bx <
b10000000000000000000000000000011 ;
bx :
bx 9
bx 8
bx 7
bx 6
bx 5
bx 4
bx 3
bx 2
bx 1
10
b0 /
0.
bx -
bx ,
bx +
bx *
bx )
bx (
bx '
bx &
bx %
bx $
bx #
b0 "
b0 !
$end
#5000
b0 D
b0 O
b0 f
b0 q
b0 w
b0 $"
b0 *"
b0 5"
b0 ;"
b0 F"
b0 L"
b0 W"
b0 ]"
b0 h"
b0 n"
b0 y"
b0 !#
b0 ,#
b0 U
b0 `
00
#50000
b10000000000 !
b10000000000 >
b10000000000 0#
b10000000000 6#
b101100111000011 2#
b0 7#
b1010 <
b0 =
b0x 2
b0x T
b0x :
b0x ~"
b0x 9
b0x m"
b0x 8
b0x \"
b0x 7
b0x K"
b0x 6
b0x :"
b0x 5
b0x )"
b0x 4
b0x v
b0x 3
b0x e
b0x 1
b0x C
1.
#100000
0.
#150000
b10110011100001 1#
b10110011100001 3#
b10110011100001 4#
b1011001110000111 2#
b0 7#
b1010 <
b10000000000 =
1.
#200000
0.
#250000
b11000000000 !
b11000000000 >
b11000000000 0#
b11000000000 6#
b101100111000011 1#
b101100111000011 3#
b101100111000011 4#
b110011100001111 2#
b0 7#
b1010 <
1.
#300000
0.
#350000
b11010 @
b11111111111111111111111111 "
b11111111111111111111111111 ?
b11010 A
b11001110000111 1#
b11001110000111 3#
b11001110000111 4#
b1100111000011110 2#
b1101001011001100 !
b1101001011001100 >
b1101001011001100 0#
b1101001011001100 6#
b0 7#
b1010 <
b11000000000 =
1.
#400000
b11111111111111111111111111 /
b11111111111111111111111111 B
b11111111111111111111111111 S
b11111111111111111111111111 d
b11111111111111111111111111 u
b11111111111111111111111111 ("
b11111111111111111111111111 9"
b11111111111111111111111111 J"
b11111111111111111111111111 ["
b11111111111111111111111111 l"
b11111111111111111111111111 }"
0.
#450000
b1101 @
b1111111111111 "
b1111111111111 ?
b1101 A
b110110101100110 !
b110110101100110 >
b110110101100110 0#
b110110101100110 6#
b110011100001111 1#
b110011100001111 3#
b110011100001111 4#
b1001110000111100 2#
b0 7#
b1010 <
b1101001011001100 =
1.
#500000
b1111111111111 /
b1111111111111 B
b1111111111111 S
b1111111111111 d
b1111111111111 u
b1111111111111 ("
b1111111111111 9"
b1111111111111 J"
b1111111111111 ["
b1111111111111 l"
b1111111111111 }"
0.
#550000
b11000 @
b111111111111111111111111 "
b111111111111111111111111 ?
b11000 A
b100111000011110 1#
b100111000011110 3#
b100111000011110 4#
b11100001111001 2#
b1100011000110010 !
b1100011000110010 >
b1100011000110010 0#
b1100011000110010 6#
b0 7#
b1010 <
b110110101100110 =
1.
#600000
b111111111111111111111111 /
b111111111111111111111111 B
b111111111111111111111111 S
b111111111111111111111111 d
b111111111111111111111111 u
b111111111111111111111111 ("
b111111111111111111111111 9"
b111111111111111111111111 J"
b111111111111111111111111 ["
b111111111111111111111111 l"
b111111111111111111111111 }"
0.
#650000
b1011 @
b11111111111 "
b11111111111 ?
b1011 A
b101101101111011 !
b101101101111011 >
b101101101111011 0#
b101101101111011 6#
b1110000111100 1#
b1110000111100 3#
b1110000111100 4#
b111000011110010 2#
b0 7#
b1010 <
b1100011000110010 =
1.
#700000
b11111111111 /
b11111111111 B
b11111111111 S
b11111111111 d
b11111111111 u
b11111111111 ("
b11111111111 9"
b11111111111 J"
b11111111111 ["
b11111111111 l"
b11111111111 }"
0.
#750000
b1100 @
b111111111111 "
b111111111111 ?
b1100 A
b11100001111001 1#
b11100001111001 3#
b11100001111001 4#
b1110000111100100 2#
b110001011010011 !
b110001011010011 >
b110001011010011 0#
b110001011010011 6#
b0 7#
b1010 <
b101101101111011 =
1.
#800000
b111111111111 /
b111111111111 B
b111111111111 S
b111111111111 d
b111111111111 u
b111111111111 ("
b111111111111 9"
b111111111111 J"
b111111111111 ["
b111111111111 l"
b111111111111 }"
0.
#850000
b11111 @
b1111111111111111111111111111111 "
b1111111111111111111111111111111 ?
b11111 A
b1111111101011010 !
b1111111101011010 >
b1111111101011010 0#
b1111111101011010 6#
b111000011110010 1#
b111000011110010 3#
b111000011110010 4#
b1100001111001000 2#
b0 7#
b1010 <
b110001011010011 =
1.
#900000
b1111111111111111111111111111111 /
b1111111111111111111111111111111 B
b1111111111111111111111111111111 S
b1111111111111111111111111111111 d
b1111111111111111111111111111111 u
b1111111111111111111111111111111 ("
b1111111111111111111111111111111 9"
b1111111111111111111111111111111 J"
b1111111111111111111111111111111 ["
b1111111111111111111111111111111 l"
b1111111111111111111111111111111 }"
0.
#950000
b10 @
b11 "
b11 ?
b10 A
b110000111100100 1#
b110000111100100 3#
b110000111100100 4#
b1000011110010001 2#
b1010010100110 !
b1010010100110 >
b1010010100110 0#
b1010010100110 6#
b0 7#
b1010 <
b1111111101011010 =
1.
#1000000
b11 /
b11 B
b11 S
b11 d
b11 u
b11 ("
b11 9"
b11 J"
b11 ["
b11 l"
b11 }"
0.
#1050000
b10110 @
b1111111111111111111111 "
b1111111111111111111111 ?
b10110 A
b1011001000100110 !
b1011001000100110 >
b1011001000100110 0#
b1011001000100110 6#
b100001111001000 1#
b100001111001000 3#
b100001111001000 4#
b111100100010 2#
b0 7#
b1010 <
b1010010100110 =
1.
#1100000
b1111111111111111111111 /
b1111111111111111111111 B
b1111111111111111111111 S
b1111111111111111111111 d
b1111111111111111111111 u
b1111111111111111111111 ("
b1111111111111111111111 9"
b1111111111111111111111 J"
b1111111111111111111111 ["
b1111111111111111111111 l"
b1111111111111111111111 }"
0.
#1150000
b100 @
b1111 "
b1111 ?
b100 A
b11110010001 1#
b11110010001 3#
b11110010001 4#
b1111001000101 2#
b10001001110101 !
b10001001110101 >
b10001001110101 0#
b10001001110101 6#
b0 7#
b1010 <
b1011001000100110 =
1.
#1200000
b1111 /
b1111 B
b1111 S
b1111 d
b1111 u
b1111 ("
b1111 9"
b1111 J"
b1111 ["
b1111 l"
b1111 }"
0.
#1250000
b100 @
b1111 "
b1111 ?
b10010110011111 !
b10010110011111 >
b10010110011111 0#
b10010110011111 6#
b111100100010 1#
b111100100010 3#
b111100100010 4#
b11110010001010 2#
b0 7#
b1010 <
b10001001110101 =
1.
#1300000
0.
#1350000
b1001 @
b111111111 "
b111111111 ?
b1001 A
b1111001000101 1#
b1111001000101 3#
b1111001000101 4#
b111100100010101 2#
b100100110011001 !
b100100110011001 >
b100100110011001 0#
b100100110011001 6#
b0 7#
b1010 <
b10010110011111 =
1.
#1400000
b111111111 /
b111111111 B
b111111111 S
b111111111 d
b111111111 u
b111111111 ("
b111111111 9"
b111111111 J"
b111111111 ["
b111111111 l"
b111111111 }"
0.
#1450000
b11010 @
b11111111111111111111111111 "
b11111111111111111111111111 ?
b11010 A
b1101001001001100 !
b1101001001001100 >
b1101001001001100 0#
b1101001001001100 6#
b11110010001010 1#
b11110010001010 3#
b11110010001010 4#
b1111001000101010 2#
b0 7#
b1010 <
b100100110011001 =
1.
#1500000
b11111111111111111111111111 /
b11111111111111111111111111 B
b11111111111111111111111111 S
b11111111111111111111111111 d
b11111111111111111111111111 u
b11111111111111111111111111 ("
b11111111111111111111111111 9"
b11111111111111111111111111 J"
b11111111111111111111111111 ["
b11111111111111111111111111 l"
b11111111111111111111111111 }"
0.
#1550000
b11110 @
b111111111111111111111111111111 "
b111111111111111111111111111111 ?
b11110 A
b111100100010101 1#
b111100100010101 3#
b111100100010101 4#
b1110010001010101 2#
b1111001010010001 !
b1111001010010001 >
b1111001010010001 0#
b1111001010010001 6#
b0 7#
b1010 <
b1101001001001100 =
1.
#1600000
b111111111111111111111111111111 /
b111111111111111111111111111111 B
b111111111111111111111111111111 S
b111111111111111111111111111111 d
b111111111111111111111111111111 u
b111111111111111111111111111111 ("
b111111111111111111111111111111 9"
b111111111111111111111111111111 J"
b111111111111111111111111111111 ["
b111111111111111111111111111111 l"
b111111111111111111111111111111 }"
0.
#1650000
b11001 @
b1111111111111111111111111 "
b1111111111111111111111111 ?
b11001 A
b1100100110101101 !
b1100100110101101 >
b1100100110101101 0#
b1100100110101101 6#
b111001000101010 1#
b111001000101010 3#
b111001000101010 4#
b1100100010101011 2#
b0 7#
b1010 <
b1111001010010001 =
1.
