result/design_copy.sv
// LFSR Module for Generating Pseudo-Random Input
module lfsr_random_input (
  input wire clk,
  input wire reset,
  output reg [15:0] lfsr_out
);
  reg [15:0] lfsr = 16'hACE1; // Initial seed for LFSR
  
  always @(posedge clk or posedge reset) begin
    if (reset) begin
      lfsr <= 16'hACE1; // Reset LFSR to initial seed
    end else begin
      // Feedback calculation for 16-bit LFSR (x^16 + x^14 + x^13 + x^11 + 1)
      lfsr <= {lfsr[14:0], lfsr[15] ^ lfsr[13] ^ lfsr[12] ^ lfsr[10]};
    end
    lfsr_out <= lfsr >> 1; // Scale to range [0, 0.5] by dividing by 2
  end
endmodule


// NARMA-10 Generator Module
module narma10_generator (
  input wire clk,
  input wire reset,
  input wire [15:0] u_t, // Input from LFSR
  output reg [15:0] y_t // 16-bit output representing the NARMA output
);
  parameter N = 10; // Order of the NARMA series
  reg [15:0] y_history [0:N-1]; // Buffer to hold past outputs
  reg [15:0] u_history [0:N-1]; // Buffer to hold past inputs
  
  integer i;
  
  always @(posedge clk or posedge reset) begin
    if (reset) begin
      // Initialize histories
      for (i = 0; i < N; i = i + 1) begin
        y_history[i] <= 16'd0;
        u_history[i] <= 16'd0;
      end
      y_t <= 16'd0;
    end else begin
      // Shift history buffers
      for (i = N-1; i > 0; i = i - 1) begin
        y_history[i] <= y_history[i-1];
        u_history[i] <= u_history[i-1];
      end
      u_history[0] <= u_t;
      
      // NARMA-10 computation: y(t+1) = 0.5*y(t) + 0.3*y(t) * sum(y(t-1) to y(t-9)) + 0.8*u(t-9)*u(t) + 0.1
      y_t <= (5 * y_history[0] / 10) +
      ((3 * y_history[0] * (y_history[1] + y_history[2] + y_history[3] +
                            y_history[4] + y_history[5] + y_history[6] +
                            y_history[7] + y_history[8] + y_history[9])) / 10) +
      (8 * u_history[9] * u_history[0] / 10) +
      (1 << 10); // Adding 0.1 as fixed-point representation
      y_history[0] <= y_t; 
    end
  end
endmodule

// Top-level Module to Integrate LFSR with NARMA
module top_level_narma_system (
  input wire clk,
  input wire reset,
  output wire [15:0] narma_output
);
  wire [15:0] lfsr_output;
  
  // Instantiate LFSR module
  lfsr_random_input lfsr_inst (
    .clk(clk),
    .reset(reset),
    .lfsr_out(lfsr_output)
  );
  
  // Instantiate NARMA-10 generator module
  narma10_generator narma_gen (
    .clk(clk),
    .reset(reset),
    .u_t(lfsr_output),
    .y_t(narma_output)
  );
endmodule



module bitstream_converter (
  input wire [15:0] y_t,
  output reg [31:0] bitstream_out
);
  integer num_on_bits;
  integer i;
  
  always @(*) begin
    // Scale y_t to determine the number of "on" bits in the 32-bit output.
    // The scaling factor should map y_t's maximum value to 32 bits fully "on".
    num_on_bits = (y_t * 32) >> 16; // Ensure y_t is scaled proportionally to 32-bit range

    // Initialize bitstream_out with all bits off
    bitstream_out = 32'b0;

    // Turn on the calculated number of bits from the most significant bit down
    for (i = 0; i < num_on_bits; i = i + 1) begin
      bitstream_out[i] = 1'b1;
    end
  end
endmodule


module SLIF_unipolar_multi(i_in, clk, rst, VOUT, i_out);
  input [7:0] i_in; // Allow 8 input signals, represented as on/off
  input clk, rst;
  output reg signed [31:0] VOUT; // The voltage across this neuron
  output reg i_out; // Output signal

  // initial condition
  reg signed [31:0] v = 	32'h00000000; // v=0;

  // LIF parameters
  reg signed [31:0] Vth = 	32'h0000fc93; // Threshold voltage = 0.98
  reg signed [31:0] leaky = 32'h00002000; // Leakage = 0.125
  reg signed [31:0] w = 	32'h00002000; // Input weight = 0.125

  integer n;
  reg signed [31:0] a; // Adder output

  // clock
  parameter s0 = 8'h00;
  parameter s1 = 8'h01;
  parameter s2 = 8'h02;

  wire [7:0] p_s;
  reg [7:0] n_s;

  assign p_s = n_s;
  always @(posedge clk or negedge rst)
  begin
      if (!rst)
          n_s <= s0;
      else if (clk)
      begin
          case (p_s)
              s0: begin
                  // Idle / refractory period
                  i_out <= 1'b0;
                  n_s <= s1;
              end
              s1: begin
                  // Accumulate weighted inputs
                  a = 32'h00000000;
                  for (n = 0; n < 8; n++)
                  begin
                      a = a + (i_in[n] * w);
                  end
                  // Integrate
                  if (a > 0)
                  begin
                      v <= v + a;
                  end
                  // Leaky
                  else if (v > 0)
                  begin
                      v <= v - leaky;
                      // Ensure that v >= 0
                      if (v < 0)
                      begin
                          v <= 32'h00000000;
                      end
                  end

                  VOUT <= v;

                  if (v >= Vth)
                  begin
                      n_s <= s2;
                  end
              end
              s2: begin
                  // Fire
                  v <= 32'h00000000;
                  VOUT <= 32'h00000000;
                  i_out <= 1'b1;

                  n_s <= s0;
              end
          endcase
      end
  end
endmodule

result/testbenchNarma.sv
module RSNN();
  reg rst;
  reg clk = 1'b0;
  reg [7:0] ext_input1 = 6'b000000; // External input to the network
  reg [7:0] ext_input2 = 6'b000000; // External input to the network
  reg [7:0] ext_input3 = 6'b000000; // External input to the network
  // Internal signals
  wire signed [31:0] VOUT_1, VOUT_2, VOUT_3; // Outputs of each neuron
  wire i_out_1, i_out_2, i_out_3; // Spike signals from each neuron
  reg [7:0] i_in_1, i_in_2, i_in_3; // Inputs to each neuron
 
  // Instantiate the neurons
  SLIF_unipolar_multi neuron1 (
      .i_in(i_in_1), 
      .clk(clk), 
      .rst(rst), 
      .VOUT(VOUT_1), 
      .i_out(i_out_1)
    );
    
  SLIF_unipolar_multi neuron2 (
    .i_in(i_in_2), 
    .clk(clk), 
    .rst(rst), 
    .VOUT(VOUT_2), 
    .i_out(i_out_2)
  );
  
  SLIF_unipolar_multi neuron3 (
    .i_in(i_in_3), 
    .clk(clk), 
    .rst(rst), 
    .VOUT(VOUT_3), 
    .i_out(i_out_3)
  );
  
  initial
  begin
    // Enable waveform dumping for simulation
    $dumpfile("dump.vcd");
    $dumpvars(0, RSNN); // Record all signals in the testbench module
    
    rst = 1'b0;
    
    
    #5 rst = 1'b1;
    #1000 ext_input1 = 6'b000001;
    #1500 ext_input2 = 6'b000001;
    #2000 ext_input3 = 6'b000001; // 1500 time units later, enable one input
    
    #10000; // Stop simulation after 10000 time units
    $finish; // Gracefully terminate the simulation
    
  end
  
  always
    begin
      #50 clk = ~clk; // Generate clock signal with 90 time unit period
      
      i_in_1 = {ext_input1, i_out_2, i_out_3};
      
      // Connect outputs of neurons as inputs to others for recurrent behavior
      i_in_2 = {ext_input2, i_out_1, i_out_3}; // Example: output of neuron 1 as input to neuron 2
      i_in_3 = {ext_input3, i_out_1, i_out_2}; // output of neuron 2 as input to neuron 3
  end

endmodule

sim_res/dump.vcd
$date
	Fri Nov 15 06:25:51 2024
$end
$version
	Icarus Verilog
$end
$timescale
	1s
$end
$scope module RSNN $end
$var wire 1 ! i_out_3 $end
$var wire 1 " i_out_2 $end
$var wire 1 # i_out_1 $end
$var wire 32 $ VOUT_3 [31:0] $end
$var wire 32 % VOUT_2 [31:0] $end
$var wire 32 & VOUT_1 [31:0] $end
$var reg 1 ' clk $end
$var reg 8 ( ext_input1 [7:0] $end
$var reg 8 ) ext_input2 [7:0] $end
$var reg 8 * ext_input3 [7:0] $end
$var reg 8 + i_in_1 [7:0] $end
$var reg 8 , i_in_2 [7:0] $end
$var reg 8 - i_in_3 [7:0] $end
$var reg 1 . rst $end
$scope module neuron1 $end
$var wire 1 ' clk $end
$var wire 8 / i_in [7:0] $end
$var wire 8 0 p_s [7:0] $end
$var wire 1 . rst $end
$var parameter 8 1 s0 $end
$var parameter 8 2 s1 $end
$var parameter 8 3 s2 $end
$var reg 32 4 VOUT [31:0] $end
$var reg 32 5 Vth [31:0] $end
$var reg 32 6 a [31:0] $end
$var reg 1 # i_out $end
$var reg 32 7 leaky [31:0] $end
$var reg 8 8 n_s [7:0] $end
$var reg 32 9 v [31:0] $end
$var reg 32 : w [31:0] $end
$var integer 32 ; n [31:0] $end
$upscope $end
$scope module neuron2 $end
$var wire 1 ' clk $end
$var wire 8 < i_in [7:0] $end
$var wire 8 = p_s [7:0] $end
$var wire 1 . rst $end
$var parameter 8 > s0 $end
$var parameter 8 ? s1 $end
$var parameter 8 @ s2 $end
$var reg 32 A VOUT [31:0] $end
$var reg 32 B Vth [31:0] $end
$var reg 32 C a [31:0] $end
$var reg 1 " i_out $end
$var reg 32 D leaky [31:0] $end
$var reg 8 E n_s [7:0] $end
$var reg 32 F v [31:0] $end
$var reg 32 G w [31:0] $end
$var integer 32 H n [31:0] $end
$upscope $end
$scope module neuron3 $end
$var wire 1 ' clk $end
$var wire 8 I i_in [7:0] $end
$var wire 8 J p_s [7:0] $end
$var wire 1 . rst $end
$var parameter 8 K s0 $end
$var parameter 8 L s1 $end
$var parameter 8 M s2 $end
$var reg 32 N VOUT [31:0] $end
$var reg 32 O Vth [31:0] $end
$var reg 32 P a [31:0] $end
$var reg 1 ! i_out $end
$var reg 32 Q leaky [31:0] $end
$var reg 8 R n_s [7:0] $end
$var reg 32 S v [31:0] $end
$var reg 32 T w [31:0] $end
$var integer 32 U n [31:0] $end
$upscope $end
$upscope $end
$enddefinitions $end
$comment Show the parameter values. $end
$dumpall
b10 M
b1 L
b0 K
b10 @
b1 ?
b0 >
b10 3
b1 2
b0 1
$end
#0
$dumpvars
bx U
b10000000000000 T
b0 S
b0 R
b10000000000000 Q
bx P
b1111110010010011 O
bx N
b0 J
bx I
bx H
b10000000000000 G
b0 F
b0 E
b10000000000000 D
bx C
b1111110010010011 B
bx A
b0 =
bx <
bx ;
b10000000000000 :
b0 9
b0 8
b10000000000000 7
bx 6
b1111110010010011 5
bx 4
b0 0
bx /
0.
bx -
bx ,
bx +
b0 *
b0 )
b0 (
0'
bx &
bx %
bx $
x#
x"
x!
$end
#5
1.
#50
b1 J
b1 R
0!
b1 =
b1 E
0"
b1 0
b1 8
0#
b0xx -
b0xx I
b0xx ,
b0xx <
b0xx +
b0xx /
1'
#100
b0 -
b0 I
b0 ,
b0 <
b0 +
b0 /
0'
#150
b0 &
b0 4
b0 %
b0 A
b0 $
b0 N
b1000 ;
b0 6
b1000 H
b0 C
b1000 U
b0 P
1'
#200
0'
#250
b1000 U
b1000 H
b1000 ;
1'
#300
0'
#350
b1000 ;
b1000 H
b1000 U
1'
#400
0'
#450
b1000 U
b1000 H
b1000 ;
1'
#500
0'
#550
b1000 ;
b1000 H
b1000 U
1'
#600
0'
#650
b1000 U
b1000 H
b1000 ;
1'
#700
0'
#750
b1000 ;
b1000 H
b1000 U
1'
#800
0'
#850
b1000 U
b1000 H
b1000 ;
1'
#900
0'
#950
b1000 ;
b1000 H
b1000 U
1'
#1000
0'
#1005
b1 (
#1050
b10000000000000 9
b1000 U
b1000 H
b10000000000000 6
b1000 ;
b100 +
b100 /
1'
#1100
0'
#1150
b10000000000000 &
b10000000000000 4
b100000000000000 9
b1000 ;
b10000000000000 6
b1000 H
b1000 U
1'
#1200
0'
#1250
b100000000000000 &
b100000000000000 4
b110000000000000 9
b1000 U
b1000 H
b1000 ;
b10000000000000 6
1'
#1300
0'
#1350
b110000000000000 &
b110000000000000 4
b1000000000000000 9
b1000 ;
b10000000000000 6
b1000 H
b1000 U
1'
#1400
0'
#1450
b1000000000000000 &
b1000000000000000 4
b1010000000000000 9
b1000 U
b1000 H
b1000 ;
b10000000000000 6
1'
#1500
0'
#1550
b1010000000000000 &
b1010000000000000 4
b1100000000000000 9
b1000 ;
b10000000000000 6
b1000 H
b1000 U
1'
#1600
0'
#1650
b1100000000000000 &
b1100000000000000 4
b1110000000000000 9
b1000 U
b1000 H
b1000 ;
b10000000000000 6
1'
#1700
0'
#1750
b1110000000000000 &
b1110000000000000 4
b10000000000000000 9
b1000 ;
b10000000000000 6
b1000 H
b1000 U
1'
#1800
0'
#1850
b10 0
b10 8
b10000000000000000 &
b10000000000000000 4
b10010000000000000 9
b1000 U
b1000 H
b1000 ;
b10000000000000 6
1'
#1900
0'
#1950
b0 0
b0 8
1#
b0 &
b0 4
b0 9
b1000 H
b1000 U
1'
#2000
b10 -
b10 I
b10 ,
b10 <
0'
#2050
b10000000000000 S
b10000000000000 F
b1 0
b1 8
0#
b10000000000000 P
b1000 U
b10000000000000 C
b1000 H
1'
#2100
b0 -
b0 I
b0 ,
b0 <
0'
#2150
b10000000000000 9
b10000000000000 %
b10000000000000 A
b0 F
b10000000000000 $
b10000000000000 N
b0 S
b1000 ;
b10000000000000 6
b1000 H
b0 C
b1000 U
b0 P
1'
#2200
0'
#2250
b0 $
b0 N
b0 %
b0 A
b10000000000000 &
b10000000000000 4
b100000000000000 9
b1000 U
b1000 H
b1000 ;
b10000000000000 6
1'
#2300
0'
#2350
b100000000000000 &
b100000000000000 4
b110000000000000 9
b1000 ;
b10000000000000 6
b1000 H
b1000 U
1'
#2400
0'
#2450
b110000000000000 &
b110000000000000 4
b1000000000000000 9
b1000 U
b1000 H
b1000 ;
b10000000000000 6
1'
#2500
0'
#2505
b1 )
#2550
b1000000000000000 &
b1000000000000000 4
b1010000000000000 9
b10000000000000 F
b1000 ;
b10000000000000 6
b10000000000000 C
b1000 H
b1000 U
b100 ,
b100 <
1'
#2600
0'
#2650
b10000000000000 %
b10000000000000 A
b100000000000000 F
b1010000000000000 &
b1010000000000000 4
b1100000000000000 9
b1000 U
b1000 H
b10000000000000 C
b1000 ;
b10000000000000 6
1'
#2700
0'
#2750
b1100000000000000 &
b1100000000000000 4
b1110000000000000 9
b100000000000000 %
b100000000000000 A
b110000000000000 F
b1000 ;
b10000000000000 6
b1000 H
b10000000000000 C
b1000 U
1'
#2800
0'
#2850
b110000000000000 %
b110000000000000 A
b1000000000000000 F
b1110000000000000 &
b1110000000000000 4
b10000000000000000 9
b1000 U
b1000 H
b10000000000000 C
b1000 ;
b10000000000000 6
1'
#2900
0'
#2950
b10 0
b10 8
b10000000000000000 &
b10000000000000000 4
b10010000000000000 9
b1000000000000000 %
b1000000000000000 A
b1010000000000000 F
b1000 ;
b10000000000000 6
b1000 H
b10000000000000 C
b1000 U
1'
#3000
0'
#3050
b1010000000000000 %
b1010000000000000 A
b1100000000000000 F
b0 0
b0 8
1#
b0 &
b0 4
b0 9
b1000 U
b1000 H
b10000000000000 C
1'
#3100
b10 -
b10 I
b110 ,
b110 <
0'
#3150
b1 0
b1 8
0#
b1100000000000000 %
b1100000000000000 A
b10000000000000000 F
b10000000000000 S
b1000 H
b100000000000000 C
b10000000000000 P
b1000 U
1'
#3200
b0 -
b0 I
b100 ,
b100 <
0'
#3250
b10000000000000 $
b10000000000000 N
b0 S
b10 =
b10 E
b10000000000000000 %
b10000000000000000 A
b10010000000000000 F
b10000000000000 9
b1000 U
b0 P
b1000 H
b10000000000000 C
b1000 ;
b10000000000000 6
1'
#3300
0'
#3350
b10000000000000 &
b10000000000000 4
b100000000000000 9
b0 =
b0 E
1"
b0 %
b0 A
b0 F
b0 $
b0 N
b1000 ;
b10000000000000 6
b1000 U
1'
#3400
b1 -
b1 I
b110 +
b110 /
0'
#3450
b10000000000000 S
b1 =
b1 E
0"
b100000000000000 &
b100000000000000 4
b1000000000000000 9
b10000000000000 P
b1000 U
b1000 ;
b100000000000000 6
1'
#3500
b0 -
b0 I
b100 +
b100 /
0'
#3550
b1000000000000000 &
b1000000000000000 4
b1010000000000000 9
b10000000000000 F
b10000000000000 $
b10000000000000 N
b0 S
b1000 ;
b10000000000000 6
b1000 H
b10000000000000 C
b1000 U
b0 P
1'
#3600
0'
#3650
b0 $
b0 N
b10000000000000 %
b10000000000000 A
b100000000000000 F
b1010000000000000 &
b1010000000000000 4
b1100000000000000 9
b1000 U
b1000 H
b10000000000000 C
b1000 ;
b10000000000000 6
1'
#3700
0'
#3750
b1100000000000000 &
b1100000000000000 4
b1110000000000000 9
b100000000000000 %
b100000000000000 A
b110000000000000 F
b1000 ;
b10000000000000 6
b1000 H
b10000000000000 C
b1000 U
1'
#3800
0'
#3850
b110000000000000 %
b110000000000000 A
b1000000000000000 F
b1110000000000000 &
b1110000000000000 4
b10000000000000000 9
b1000 U
b1000 H
b10000000000000 C
b1000 ;
b10000000000000 6
1'
#3900
0'
#3950
b10 0
b10 8
b10000000000000000 &
b10000000000000000 4
b10010000000000000 9
b1000000000000000 %
b1000000000000000 A
b1010000000000000 F
b1000 ;
b10000000000000 6
b1000 H
b10000000000000 C
b1000 U
1'
#4000
0'
#4050
b1010000000000000 %
b1010000000000000 A
b1100000000000000 F
b0 0
b0 8
1#
b0 &
b0 4
b0 9
b1000 U
b1000 H
b10000000000000 C
1'
#4100
b10 -
b10 I
b110 ,
b110 <
0'
#4150
b1 0
b1 8
0#
b1100000000000000 %
b1100000000000000 A
b10000000000000000 F
b10000000000000 S
b1000 H
b100000000000000 C
b10000000000000 P
b1000 U
1'
#4200
b0 -
b0 I
b100 ,
b100 <
0'
#4250
b10000000000000 $
b10000000000000 N
b0 S
b10 =
b10 E
b10000000000000000 %
b10000000000000000 A
b10010000000000000 F
b10000000000000 9
b1000 U
b0 P
b1000 H
b10000000000000 C
b1000 ;
b10000000000000 6
1'
#4300
0'
#4350
b10000000000000 &
b10000000000000 4
b100000000000000 9
b0 =
b0 E
1"
b0 %
b0 A
b0 F
b0 $
b0 N
b1000 ;
b10000000000000 6
b1000 U
1'
#4400
b1 -
b1 I
b110 +
b110 /
0'
#4450
b10000000000000 S
b1 =
b1 E
0"
b100000000000000 &
b100000000000000 4
b1000000000000000 9
b10000000000000 P
b1000 U
b1000 ;
b100000000000000 6
1'
#4500
b0 -
b0 I
b100 +
b100 /
0'
#4505
b1 *
#4550
b1000000000000000 &
b1000000000000000 4
b1010000000000000 9
b10000000000000 F
b10000000000000 $
b10000000000000 N
b100000000000000 S
b1000 ;
b10000000000000 6
b1000 H
b10000000000000 C
b1000 U
b10000000000000 P
b100 -
b100 I
1'
#4600
0'
#4650
b100000000000000 $
b100000000000000 N
b110000000000000 S
b10000000000000 %
b10000000000000 A
b100000000000000 F
b1010000000000000 &
b1010000000000000 4
b1100000000000000 9
b1000 U
b10000000000000 P
b1000 H
b10000000000000 C
b1000 ;
b10000000000000 6
1'
#4700
0'
#4750
b1100000000000000 &
b1100000000000000 4
b1110000000000000 9
b100000000000000 %
b100000000000000 A
b110000000000000 F
b110000000000000 $
b110000000000000 N
b1000000000000000 S
b1000 ;
b10000000000000 6
b1000 H
b10000000000000 C
b1000 U
b10000000000000 P
1'
#4800
0'
#4850
b1000000000000000 $
b1000000000000000 N
b1010000000000000 S
b110000000000000 %
b110000000000000 A
b1000000000000000 F
b1110000000000000 &
b1110000000000000 4
b10000000000000000 9
b1000 U
b10000000000000 P
b1000 H
b10000000000000 C
b1000 ;
b10000000000000 6
1'
#4900
0'
#4950
b10 0
b10 8
b10000000000000000 &
b10000000000000000 4
b10010000000000000 9
b1000000000000000 %
b1000000000000000 A
b1010000000000000 F
b1010000000000000 $
b1010000000000000 N
b1100000000000000 S
b1000 ;
b10000000000000 6
b1000 H
b10000000000000 C
b1000 U
b10000000000000 P
1'
#5000
0'
#5050
b1100000000000000 $
b1100000000000000 N
b1110000000000000 S
b1010000000000000 %
b1010000000000000 A
b1100000000000000 F
b0 0
b0 8
1#
b0 &
b0 4
b0 9
b1000 U
b10000000000000 P
b1000 H
b10000000000000 C
1'
#5100
b110 -
b110 I
b110 ,
b110 <
0'
#5150
b1 0
b1 8
0#
b1100000000000000 %
b1100000000000000 A
b10000000000000000 F
b1110000000000000 $
b1110000000000000 N
b10010000000000000 S
b1000 H
b100000000000000 C
b1000 U
b100000000000000 P
1'
#5200
b100 -
b100 I
b100 ,
b100 <
0'
#5250
b10 J
b10 R
b10010000000000000 $
b10010000000000000 N
b10100000000000000 S
b10 =
b10 E
b10000000000000000 %
b10000000000000000 A
b10010000000000000 F
b10000000000000 9
b1000 U
b10000000000000 P
b1000 H
b10000000000000 C
b1000 ;
b10000000000000 6
1'
#5300
0'
#5350
b10000000000000 &
b10000000000000 4
b100000000000000 9
b0 =
b0 E
1"
b0 %
b0 A
b0 F
b0 J
b0 R
1!
b0 $
b0 N
b0 S
b1000 ;
b10000000000000 6
1'
#5400
b101 -
b101 I
b101 ,
b101 <
b111 +
b111 /
0'
#5450
b1 J
b1 R
0!
b1 =
b1 E
0"
b100000000000000 &
b100000000000000 4
b1010000000000000 9
b1000 ;
b110000000000000 6
1'
#5500
b100 -
b100 I
b100 ,
b100 <
b100 +
b100 /
0'
#5550
b1010000000000000 &
b1010000000000000 4
b1100000000000000 9
b10000000000000 F
b10000000000000 S
b1000 ;
b10000000000000 6
b1000 H
b10000000000000 C
b1000 U
b10000000000000 P
1'
#5600
0'
#5650
b10000000000000 $
b10000000000000 N
b100000000000000 S
b10000000000000 %
b10000000000000 A
b100000000000000 F
b1100000000000000 &
b1100000000000000 4
b1110000000000000 9
b1000 U
b10000000000000 P
b1000 H
b10000000000000 C
b1000 ;
b10000000000000 6
1'
#5700
0'
#5750
b1110000000000000 &
b1110000000000000 4
b10000000000000000 9
b100000000000000 %
b100000000000000 A
b110000000000000 F
b100000000000000 $
b100000000000000 N
b110000000000000 S
b1000 ;
b10000000000000 6
b1000 H
b10000000000000 C
b1000 U
b10000000000000 P
1'
#5800
0'
#5850
b110000000000000 $
b110000000000000 N
b1000000000000000 S
b110000000000000 %
b110000000000000 A
b1000000000000000 F
b10 0
b10 8
b10000000000000000 &
b10000000000000000 4
b10010000000000000 9
b1000 U
b10000000000000 P
b1000 H
b10000000000000 C
b1000 ;
b10000000000000 6
1'
#5900
0'
#5950
b0 0
b0 8
1#
b0 &
b0 4
b0 9
b1000000000000000 %
b1000000000000000 A
b1010000000000000 F
b1000000000000000 $
b1000000000000000 N
b1010000000000000 S
b1000 H
b10000000000000 C
b1000 U
b10000000000000 P
1'
#6000
b110 -
b110 I
b110 ,
b110 <
0'
#6050
b1010000000000000 $
b1010000000000000 N
b1110000000000000 S
b1010000000000000 %
b1010000000000000 A
b1110000000000000 F
b1 0
b1 8
0#
b1000 U
b100000000000000 P
b1000 H
b100000000000000 C
1'
#6100
b100 -
b100 I
b100 ,
b100 <
0'
#6150
b10000000000000 9
b1110000000000000 %
b1110000000000000 A
b10000000000000000 F
b1110000000000000 $
b1110000000000000 N
b10000000000000000 S
b1000 ;
b10000000000000 6
b1000 H
b10000000000000 C
b1000 U
b10000000000000 P
1'
#6200
0'
#6250
b10 J
b10 R
b10000000000000000 $
b10000000000000000 N
b10010000000000000 S
b10 =
b10 E
b10000000000000000 %
b10000000000000000 A
b10010000000000000 F
b10000000000000 &
b10000000000000 4
b100000000000000 9
b1000 U
b10000000000000 P
b1000 H
b10000000000000 C
b1000 ;
b10000000000000 6
1'
#6300
0'
#6350
b100000000000000 &
b100000000000000 4
b110000000000000 9
b0 =
b0 E
1"
b0 %
b0 A
b0 F
b0 J
b0 R
1!
b0 $
b0 N
b0 S
b1000 ;
b10000000000000 6
1'
#6400
b101 -
b101 I
b101 ,
b101 <
b111 +
b111 /
0'
#6450
b1 J
b1 R
0!
b1 =
b1 E
0"
b110000000000000 &
b110000000000000 4
b1100000000000000 9
b1000 ;
b110000000000000 6
1'
#6500
b100 -
b100 I
b100 ,
b100 <
b100 +
b100 /
0'
#6550
b1100000000000000 &
b1100000000000000 4
b1110000000000000 9
b10000000000000 F
b10000000000000 S
b1000 ;
b10000000000000 6
b1000 H
b10000000000000 C
b1000 U
b10000000000000 P
1'
#6600
0'
#6650
b10000000000000 $
b10000000000000 N
b100000000000000 S
b10000000000000 %
b10000000000000 A
b100000000000000 F
b1110000000000000 &
b1110000000000000 4
b10000000000000000 9
b1000 U
b10000000000000 P
b1000 H
b10000000000000 C
b1000 ;
b10000000000000 6
1'
#6700
0'
#6750
b10 0
b10 8
b10000000000000000 &
b10000000000000000 4
b10010000000000000 9
b100000000000000 %
b100000000000000 A
b110000000000000 F
b100000000000000 $
b100000000000000 N
b110000000000000 S
b1000 ;
b10000000000000 6
b1000 H
b10000000000000 C
b1000 U
b10000000000000 P
1'
#6800
0'
#6850
b110000000000000 $
b110000000000000 N
b1000000000000000 S
b110000000000000 %
b110000000000000 A
b1000000000000000 F
b0 0
b0 8
1#
b0 &
b0 4
b0 9
b1000 U
b10000000000000 P
b1000 H
b10000000000000 C
1'
#6900
b110 -
b110 I
b110 ,
b110 <
0'
#6950
b1 0
b1 8
0#
b1000000000000000 %
b1000000000000000 A
b1100000000000000 F
b1000000000000000 $
b1000000000000000 N
b1100000000000000 S
b1000 H
b100000000000000 C
b1000 U
b100000000000000 P
1'
#7000
b100 -
b100 I
b100 ,
b100 <
0'
#7050
b1100000000000000 $
b1100000000000000 N
b1110000000000000 S
b1100000000000000 %
b1100000000000000 A
b1110000000000000 F
b10000000000000 9
b1000 U
b10000000000000 P
b1000 H
b10000000000000 C
b1000 ;
b10000000000000 6
1'
#7100
0'
#7150
b10000000000000 &
b10000000000000 4
b100000000000000 9
b1110000000000000 %
b1110000000000000 A
b10000000000000000 F
b1110000000000000 $
b1110000000000000 N
b10000000000000000 S
b1000 ;
b10000000000000 6
b1000 H
b10000000000000 C
b1000 U
b10000000000000 P
1'
#7200
0'
#7250
b10 J
b10 R
b10000000000000000 $
b10000000000000000 N
b10010000000000000 S
b10 =
b10 E
b10000000000000000 %
b10000000000000000 A
b10010000000000000 F
b100000000000000 &
b100000000000000 4
b110000000000000 9
b1000 U
b10000000000000 P
b1000 H
b10000000000000 C
b1000 ;
b10000000000000 6
1'
#7300
0'
#7350
b110000000000000 &
b110000000000000 4
b1000000000000000 9
b0 =
b0 E
1"
b0 %
b0 A
b0 F
b0 J
b0 R
1!
b0 $
b0 N
b0 S
b1000 ;
b10000000000000 6
1'
#7400
b101 -
b101 I
b101 ,
b101 <
b111 +
b111 /
0'
#7450
b1 J
b1 R
0!
b1 =
b1 E
0"
b1000000000000000 &
b1000000000000000 4
b1110000000000000 9
b1000 ;
b110000000000000 6
1'
#7500
b100 -
b100 I
b100 ,
b100 <
b100 +
b100 /
0'
#7550
b1110000000000000 &
b1110000000000000 4
b10000000000000000 9
b10000000000000 F
b10000000000000 S
b1000 ;
b10000000000000 6
b1000 H
b10000000000000 C
b1000 U
b10000000000000 P
1'
#7600
0'
#7650
b10000000000000 $
b10000000000000 N
b100000000000000 S
b10000000000000 %
b10000000000000 A
b100000000000000 F
b10 0
b10 8
b10000000000000000 &
b10000000000000000 4
b10010000000000000 9
b1000 U
b10000000000000 P
b1000 H
b10000000000000 C
b1000 ;
b10000000000000 6
1'
#7700
0'
#7750
b0 0
b0 8
1#
b0 &
b0 4
b0 9
b100000000000000 %
b100000000000000 A
b110000000000000 F
b100000000000000 $
b100000000000000 N
b110000000000000 S
b1000 H
b10000000000000 C
b1000 U
b10000000000000 P
1'
#7800
b110 -
b110 I
b110 ,
b110 <
0'
#7850
b110000000000000 $
b110000000000000 N
b1010000000000000 S
b110000000000000 %
b110000000000000 A
b1010000000000000 F
b1 0
b1 8
0#
b1000 U
b100000000000000 P
b1000 H
b100000000000000 C
1'
#7900
b100 -
b100 I
b100 ,
b100 <
0'
#7950
b10000000000000 9
b1010000000000000 %
b1010000000000000 A
b1100000000000000 F
b1010000000000000 $
b1010000000000000 N
b1100000000000000 S
b1000 ;
b10000000000000 6
b1000 H
b10000000000000 C
b1000 U
b10000000000000 P
1'
#8000
0'
#8050
b1100000000000000 $
b1100000000000000 N
b1110000000000000 S
b1100000000000000 %
b1100000000000000 A
b1110000000000000 F
b10000000000000 &
b10000000000000 4
b100000000000000 9
b1000 U
b10000000000000 P
b1000 H
b10000000000000 C
b1000 ;
b10000000000000 6
1'
#8100
0'
#8150
b100000000000000 &
b100000000000000 4
b110000000000000 9
b1110000000000000 %
b1110000000000000 A
b10000000000000000 F
b1110000000000000 $
b1110000000000000 N
b10000000000000000 S
b1000 ;
b10000000000000 6
b1000 H
b10000000000000 C
b1000 U
b10000000000000 P
1'
#8200
0'
#8250
b10 J
b10 R
b10000000000000000 $
b10000000000000000 N
b10010000000000000 S
b10 =
b10 E
b10000000000000000 %
b10000000000000000 A
b10010000000000000 F
b110000000000000 &
b110000000000000 4
b1000000000000000 9
b1000 U
b10000000000000 P
b1000 H
b10000000000000 C
b1000 ;
b10000000000000 6
1'
#8300
0'
#8350
b1000000000000000 &
b1000000000000000 4
b1010000000000000 9
b0 =
b0 E
1"
b0 %
b0 A
b0 F
b0 J
b0 R
1!
b0 $
b0 N
b0 S
b1000 ;
b10000000000000 6
1'
#8400
b101 -
b101 I
b101 ,
b101 <
b111 +
b111 /
0'
#8450
b1 J
b1 R
0!
b1 =
b1 E
0"
b1010000000000000 &
b1010000000000000 4
b10000000000000000 9
b1000 ;
b110000000000000 6
1'
#8500
b100 -
b100 I
b100 ,
b100 <
b100 +
b100 /
0'
#8550
b10 0
b10 8
b10000000000000000 &
b10000000000000000 4
b10010000000000000 9
b10000000000000 F
b10000000000000 S
b1000 ;
b10000000000000 6
b1000 H
b10000000000000 C
b1000 U
b10000000000000 P
1'
#8600
0'
#8650
b10000000000000 $
b10000000000000 N
b100000000000000 S
b10000000000000 %
b10000000000000 A
b100000000000000 F
b0 0
b0 8
1#
b0 &
b0 4
b0 9
b1000 U
b10000000000000 P
b1000 H
b10000000000000 C
1'
#8700
b110 -
b110 I
b110 ,
b110 <
0'
#8750
b1 0
b1 8
0#
b100000000000000 %
b100000000000000 A
b1000000000000000 F
b100000000000000 $
b100000000000000 N
b1000000000000000 S
b1000 H
b100000000000000 C
b1000 U
b100000000000000 P
1'
#8800
b100 -
b100 I
b100 ,
b100 <
0'
#8850
b1000000000000000 $
b1000000000000000 N
b1010000000000000 S
b1000000000000000 %
b1000000000000000 A
b1010000000000000 F
b10000000000000 9
b1000 U
b10000000000000 P
b1000 H
b10000000000000 C
b1000 ;
b10000000000000 6
1'
#8900
0'
